Metadata-Version: 2.3
Name: smartrent-py-fixed
Version: 0.5.1
Summary: Unofficial Python API for SmartRent devices
License: MIT
Author: Anthony Michael
Author-email: tonykz87@gmail.com
Requires-Python: >=3.6.1,<4.0.0
Classifier: License :: OSI Approved :: MIT License
Classifier: Programming Language :: Python :: 3
Classifier: Programming Language :: Python :: 3.7
Classifier: Programming Language :: Python :: 3.8
Classifier: Programming Language :: Python :: 3.9
Classifier: Programming Language :: Python :: 3.10
Classifier: Programming Language :: Python :: 3.11
Classifier: Programming Language :: Python :: 3.12
Classifier: Programming Language :: Python :: 3.13
Requires-Dist: aiohttp (>=3.8.4,<4.0.0)
Requires-Dist: websockets (>=15.0.1,<16.0.0)
Project-URL: Documentation, https://smartrentpy.readthedocs.io
Project-URL: Repository, https://github.com/anthonymkz/smartrent-py
